setup.py
GitHubSyncPlugin.egg-info/PKG-INFO
GitHubSyncPlugin.egg-info/SOURCES.txt
GitHubSyncPlugin.egg-info/dependency_links.txt
GitHubSyncPlugin.egg-info/entry_points.txt
GitHubSyncPlugin.egg-info/not-zip-safe
GitHubSyncPlugin.egg-info/top_level.txt
githubsync/__init__.py
githubsync/api.py