Metadata-Version: 1.0
Name: GitHubSyncPlugin
Version: 0.1.3
Summary: Sync GitHub repository with local repository used by Trac.
Home-page: http://mitar.tnode.com/
Author: Mitar
Author-email: mitar.trac@tnode.com
License: AGPLv3
Keywords: trac plugin
Platform: UNKNOWN
